
COPYING.GPL
COPYING.SPL.txt
COPYING.TGPPL.html
README.txt
setup.py
test.sh
trialcoverage/__init__.py
trialcoverage/_version.py
trialcoverage/trialcoverage.py
trialcoverage.egg-info/PKG-INFO
trialcoverage.egg-info/SOURCES.txt
trialcoverage.egg-info/dependency_links.txt
trialcoverage.egg-info/not-zip-safe
trialcoverage.egg-info/requires.txt
trialcoverage.egg-info/top_level.txt
trialcoverage/test/__init__.py
trialcoverage/test/test_import_all.py
trialcoverage/test/test_tests.py
twisted/plugins/trialcoveragereporterplugin.py